mh/__init__.py
mh/core.py
mh/core_legacy.py
mh/errors.py
mh/import_env.py
mh/jupyter.py
mh/typlotlib.py
mh/typlotlib_legacy.py
masthay_helpers-0.2.114.dist-info/METADATA
masthay_helpers-0.2.114.dist-info/WHEEL
masthay_helpers-0.2.114.dist-info/top_level.txt
masthay_helpers-0.2.114.dist-info/RECORD
