Metadata-Version: 2.1
Name: masthay-helpers
Version: 0.2.114
Summary: Helper functions for repetitive and useful tasks
Author: Tyler Masthay
Classifier: Programming Language :: Python :: 3
Classifier: License :: OSI Approved :: MIT License
Classifier: Operating System :: OS Independent
Requires-Python: >=3.10
Requires-Dist: holoviews>=1.17.1
Requires-Dist: hvplot>=0.8.4
Requires-Dist: hydra-core>=1.1.0
Requires-Dist: matplotlib>=3.7.2
Requires-Dist: matplotlib-inline>=0.1.6
Requires-Dist: numpy==1.25.2
Requires-Dist: pandas==1.5.3
Requires-Dist: panel>=1.2.3
Requires-Dist: returns>=0.22.0
Requires-Dist: tabulate>=0.8.9
Requires-Dist: termcolor>=1.1.0
